pyskydl/__init__.py
pyskydl/common/__init__.py
pyskydl/common/version.py
pyskydl/core/__init__.py
pyskydl/core/default_data_module.py
pyskydl/core/default_model.py
pyskydl/core/default_net.py
pyskydl/core/default_torch_lightning_model.py
pyskydl/core/default_torch_lightning_net.py
pyskydl/core/dist_strategy_config.py
pyskydl/core/enums.py
pyskydl/core/estimator_modelv2_mixin.py
pyskydl/core/estimator_netv2.py
pyskydl/core/keras_feature_input_layer_merged_modelv2.py
pyskydl/core/layersv2.py
pyskydl/core/lossesv2.py
pyskydl/core/modelv2.py
pyskydl/core/netv2.py
pyskydl/core/super_tf_dataset_builder.py
pyskydl/core/tf_keras_activationv2_mixin.py
pyskydl/core/tf_keras_layer_mixin.py
pyskydl/core/tf_keras_layersv2.py
pyskydl/core/tf_keras_lossesv2.py
pyskydl/core/tf_keras_modelv2.py
pyskydl/core/tf_keras_modelv2_mixin.py
pyskydl/core/tf_keras_netv2.py
pyskydl/core/tf_utils.py
pyskydl/core/torch_lightning_modelv2_mixin.py
pyskydl/core/torch_lightning_netv2.py
pyskydl/core/torch_modelv2.py
pyskydl/core/torch_modelv2_mixin.py
pyskydl/core/torch_netv2.py
pyskydl/core/torch_utils.py
pyskydl/core/v1/__init__.py
pyskydl/core/v1/super_model.py
pyskydl/core/v1/super_net.py
pyskydl/core/v1/super_torch_model.py
pyskydl/core/v1/super_torch_net.py
pyskydl/core/v1/torch_model_mixin.py
pyskydl/datasets/__init__.py
pyskydl/datasets/chinese_bert_classifier_dataset_builder.py
pyskydl/datasets/chinese_bert_ner_dataset_builder.py
pyskydl/datasets/recommend_dataset_builder.py
pyskydl/examples/__init__.py
pyskydl/examples/pytorch/__init__.py
pyskydl/examples/pytorch/simple_image_classifier.py
pyskydl/examples/pytorch/boring_model/__init__.py
pyskydl/examples/pytorch/boring_model/boring_main.py
pyskydl/examples/pytorch/boring_model/boring_model.py
pyskydl/examples/pytorch/boring_model/boring_net.py
pyskydl/examples/pytorch/hello_pytorch/__init__.py
pyskydl/examples/pytorch/hello_pytorch/hello_pytorch_main.py
pyskydl/examples/pytorch/hello_pytorch/hello_pytorch_model.py
pyskydl-1.0.0.dist-info/LICENSE
pyskydl-1.0.0.dist-info/METADATA
pyskydl-1.0.0.dist-info/WHEEL
pyskydl-1.0.0.dist-info/top_level.txt
pyskydl-1.0.0.dist-info/RECORD
